topsis_navkiran.py
topsis_navkiran_cli.py
topsis_navkiran-1.1.4.dist-info/LICENSE
topsis_navkiran-1.1.4.dist-info/METADATA
topsis_navkiran-1.1.4.dist-info/WHEEL
topsis_navkiran-1.1.4.dist-info/entry_points.txt
topsis_navkiran-1.1.4.dist-info/top_level.txt
topsis_navkiran-1.1.4.dist-info/RECORD
