Metadata-Version: 2.1
Name: topsis-navkiran
Version: 1.1.4
Summary: TOPSIS implementation in python for multi-criteria decision making
Home-page: https://github.com/navkiran/topsis_project_navkiran
Author: Navkiran Singh
Author-email: nsingh2_be17@thapar.edu
License: UNKNOWN
Keywords: command-line,topsis-python,TOPSIS
Platform: UNKNOWN
Classifier: Programming Language :: Python :: 3
Classifier: License :: OSI Approved :: MIT License
Classifier: Operating System :: OS Independent
Requires-Python: >=3.6
Requires-Dist: numpy
Requires-Dist: pandas
